topsis_PranavDevKhindria_102203279/__init__.py
topsis_PranavDevKhindria_102203279/main.py
topsis_PranavDevKhindria_102203279-0.2.0.dist-info/LICENSE.md
topsis_PranavDevKhindria_102203279-0.2.0.dist-info/METADATA
topsis_PranavDevKhindria_102203279-0.2.0.dist-info/WHEEL
topsis_PranavDevKhindria_102203279-0.2.0.dist-info/entry_points.txt
topsis_PranavDevKhindria_102203279-0.2.0.dist-info/top_level.txt
topsis_PranavDevKhindria_102203279-0.2.0.dist-info/RECORD
