Metadata-Version: 2.2
Name: topsis-PranavDevKhindria-102203279
Version: 0.2.0
Summary: A Python package to perform Topsis analysis.
Home-page: https://github.com/oxzoid/Topsis-package
Author: Pranav
Classifier: Programming Language :: Python :: 3
Classifier: License :: OSI Approved :: MIT License
Classifier: Operating System :: OS Independent
Requires-Python: >=3.6
License-File: LICENSE.md
Requires-Dist: pandas
Requires-Dist: numpy
Dynamic: author
Dynamic: classifier
Dynamic: description
Dynamic: description-content-type
Dynamic: home-page
Dynamic: requires-dist
Dynamic: requires-python
Dynamic: summary
